{
  "schema": "raw-evidence.raw.ida_closure.v1",
  "leaf": "builtin__image_support__plugin_info",
  "platform": "macos",
  "owner": {
    "addr": "0x1003863bc",
    "decompile_ok": true,
    "pseudocode_lines": 84,
    "pseudocode_chars": 3176
  },
  "important_callees": "",
  "threading_model": "image_support plugin_info",
  "terminal_side_effect_classes": "image-support builtin plugin info DTO/default enabled/settings",
  "gate": {
    "consumerStartReady": true,
    "strictImplementationUse": true,
    "readyToImplement": true,
    "implementation_use": true,
    "gate_accepted": true,
    "full_leaf_100": true,
    "moduleExitAllowed": true,
    "platformScopeDeclared": true,
    "allowedImplementationMode": "Implement current macos AiMaMi 1.0.9 plugins behavior from IDA owner/callee/DTO/side-effect evidence only."
  },
  "idb_saved": true
}
